Metadata-Version: 1.0
Name: qot
Version: 0.0.0
Summary: qot
Home-page: UNKNOWN
Author: qot
Author-email: UNKNOWN
License: qot
Platform: UNKNOWN
